ribalta/__init__.py
ribalta/riba.py
ribalta/templates/__init__.py
ribalta/templates/cbi.mako
ribalta/utils/__init__.py
ribalta/utils/errors.py
ribalta/utils/odoo_stuff.py
ribalta/utils/validators.py
ribalta-0.4.5.dist-info/LICENSE
ribalta-0.4.5.dist-info/WHEEL
ribalta-0.4.5.dist-info/METADATA
ribalta-0.4.5.dist-info/RECORD
