Metadata-Version: 2.1
Name: ribalta
Version: 0.4.5
Summary: RiBa tools!
Home-page: https://github.com/LibrERP/Pylibs/
Author: Marco Tosato
Author-email: marco.tosato@didotech.com
Requires-Python: >= 3.6
Classifier: Programming Language :: Python :: 3
Classifier: Operating System :: OS Independent
Classifier: Development Status :: 5 - Production/Stable
Classifier: License :: OSI Approved :: GNU Lesser General Public License v3 (LGPLv3)
Classifier: Framework :: Odoo
Requires-Dist: mako >=1.1.3
Requires-Dist: unidecode
Requires-Dist: pytest >=2.7.3 ; extra == "test"
Requires-Dist: pytest-cov ; extra == "test"
Requires-Dist: python-dateutil ; extra == "test"
Provides-Extra: dev
Provides-Extra: doc
Provides-Extra: test
